set_calibration/__init__.py
set_calibration/_version.py
set_calibration/_widget.py
set_calibration/napari.yaml
set_calibration/_tests/__init__.py
set_calibration/_tests/test_widget.py
set_calibration-0.0.4.dist-info/licenses/LICENSE
set_calibration-0.0.4.dist-info/METADATA
set_calibration-0.0.4.dist-info/WHEEL
set_calibration-0.0.4.dist-info/entry_points.txt
set_calibration-0.0.4.dist-info/top_level.txt
set_calibration-0.0.4.dist-info/RECORD
