Metadata-Version: 2.4
Name: set-calibration
Version: 0.0.4
Summary: A tool allowing to modify the calibration (physical units) of images
Author: Clement H. Benedetti
Author-email: clement.benedetti@mri.cnrs.fr
License: 
Project-URL: Bug Tracker, https://github.com/MontpellierRessourcesImagerie/set-calibration/issues
Project-URL: Documentation, https://github.com/MontpellierRessourcesImagerie/set-calibration#README.md
Project-URL: Source Code, https://github.com/MontpellierRessourcesImagerie/set-calibration
Project-URL: User Support, https://github.com/MontpellierRessourcesImagerie/set-calibration/issues
Classifier: Development Status :: 2 - Pre-Alpha
Classifier: Framework :: napari
Classifier: Intended Audience :: Developers
Classifier: License :: OSI Approved :: MIT License
Classifier: Operating System :: OS Independent
Classifier: Programming Language :: Python
Classifier: Programming Language :: Python :: 3
Classifier: Programming Language :: Python :: 3 :: Only
Classifier: Programming Language :: Python :: 3.10
Classifier: Programming Language :: Python :: 3.11
Classifier: Programming Language :: Python :: 3.12
Classifier: Topic :: Scientific/Engineering :: Image Processing
Requires-Python: >=3.10
License-File: LICENSE
Requires-Dist: numpy
Requires-Dist: magicgui
Requires-Dist: qtpy
Requires-Dist: scikit-image
Provides-Extra: testing
Requires-Dist: tox; extra == "testing"
Requires-Dist: pytest; extra == "testing"
Requires-Dist: pytest-cov; extra == "testing"
Requires-Dist: pytest-qt; extra == "testing"
Requires-Dist: napari; extra == "testing"
Requires-Dist: pyqt5; extra == "testing"
Requires-Dist: qtpy; extra == "testing"
Dynamic: license-file
